{
    "version": "2022.08.07.01.14.01",
    "description": "",
    "homepage": "",
    "license": "MIT",
    "depends": [
    ],
    "url": [
        "https://github.com/spider-explorer/spider3/releases/download/v2022.08.07.01.14.01/spider-v2022.08.07.01.14.01.zip"
    ],
    "hash": [
        "59cbd3f6e03ccd92d95ee590fea628b31f7c2c294233b6ef1c4ed42a64836cdd"
    ],
    "bin": [
        [
            "boot3-x86_64-static.exe",
            "spider3",
            "--dumy"
        ]
    ],
    "shortcuts": [
        [
            "boot3-x86_64-static.exe",
            "spider3",
            "--dummy"
        ]
    ],
    "persist": "temp"
}
