{
    "version": "2022.08.08.04.07.06",
    "description": "",
    "homepage": "",
    "license": "MIT",
    "depends": [
    ],
    "url": [
        "https://github.com/spider-explorer/spider3/releases/download/v2022.08.08.04.07.06/spider-v2022.08.08.04.07.06.zip"
    ],
    "hash": [
        "ffa1d81121aa19edf4540e90b5b6124a17ec9486978a0b1106c6d6bd0f4b8ef5"
    ],
    "bin": [
        [
            "boot3-x86_64-static.exe",
            "spider3",
            "--dumy"
        ]
    ],
    "shortcuts": [
        [
            "boot3-x86_64-static.exe",
            "spider3",
            "--dummy"
        ]
    ],
    "persist": "temp"
}
